<Profile><Filters/><OutputFormat IsUsing="1"><AdvancedJ2KOptions><Parameter Name="CompressionControl" Value="3"/><Parameter Name="ProgressingOrder" Value="2"/><Parameter Name="CompressionRatio" Value="25"/><Parameter Name="TargetSize" Value="10240"/><Parameter Name="UseColorTransform" Value="1"/><Parameter Name="DerivedQuantinization" Value="1"/><Parameter Name="XOsiz" Value="0"/><Parameter Name="YOsiz" Value="0"/><Parameter Name="XTsiz" Value="1000000"/><Parameter Name="YTsiz" Value="1000000"/><Parameter Name="XTOsiz" Value="0"/><Parameter Name="YTOsiz" Value="0"/><Parameter Name="DecompressLevel" Value="5"/><Parameter Name="CodBlockWidth" Value="64"/><Parameter Name="CodBlockHeight" Value="64"/><Parameter Name="SelectiveACBypass" Value="0"/><Parameter Name="ResetContextOnBoundaries" Value="0"/><Parameter Name="TerminationOnEachPass" Value="0"/><Parameter Name="VerticallyCasualContext" Value="0"/><Parameter Name="PredictableTermination" Value="0"/><Parameter Name="ErrorResilienceSymbol" Value="0"/><Parameter Name="GuardBits" Value="2"/><Parameter Name="DerivedBaseMantissa" Value="0"/><Parameter Name="DerivedBaseExponent" Value="8"/><Parameter Name="UseSOPMarker" Value="0"/><Parameter Name="UseEPHMarker" Value="0"/><Parameter Name="UseROI" Value="0"/><Parameter Name="ROIControl" Value="0"/><Parameter Name="ROIWeight" Value="0.5"/><Parameter Name="ROIleft" Value="0"/><Parameter Name="ROItop" Value="0"/><Parameter Name="ROIright" Value="0"/><Parameter Name="ROIbottom" Value="0"/><Parameter Name="AlphaChannelLossless" Value="0"/><Parameter Name="AlphaChannelActiveBits" Value="16"/><Parameter Name="PrecinctSize" Value="7"/></AdvancedJ2KOptions><Parameter Name="Type" Value="66"/><Parameter Name="SubfileType" Value="1"/><Parameter Name="QFactor" Value="2"/><Parameter Name="ProgressiveOption" Value="1"/></OutputFormat><Advanced><VectorSettings><Parameter Name="ResolutionX" Value="150"/><Parameter Name="ResolutionY" Value="150"/><Parameter Name="PageSize" Value="4"/></VectorSettings><XPSSettings><Parameter Name="ResolutionX" Value="150"/><Parameter Name="ResolutionY" Value="150"/></XPSSettings><PDFSettings><Parameter Name="ResolutionX" Value="150"/><Parameter Name="ResolutionY" Value="150"/><Parameter Name="ColorDepth" Value="24"/><Parameter Name="TextAlpha" Value="4"/><Parameter Name="GraphicsAlpha" Value="1"/></PDFSettings></Advanced></Profile>
