<?xml version="1.0" encoding="utf-8"?>
<AutoStore NSI_SIG2="0D768C6FCA38F0BA5DD25665F56B623FFEE47F9309286E465E145AD5DDAEB71F0DB42C26A64F093CA866A3AE28B1C6E7">
	<Header Version="2" DateCreated="2019-01-04" TimeCreated="14:09:58" AUTHOR="" COMMENTS=""/>
	<KnowledgeObjects ObjID="1435782872-26301-19153-181-234">
		<KnowledgeObject ObjID="4088323595-57129-17284-143-80">
			<KnowledgeFields>
				<Field Name="WitnessMobile2" Value=""/>
				<Field Name="WitnessPhone2" Value=""/>
				<Field Name="WitnessAddress2" Value=""/>
				<Field Name="WitnessName2" Value=""/>
				<Field Name="WitnessMobile1" Value=""/>
				<Field Name="WitnessPhone1" Value=""/>
				<Field Name="WitnessAddress1" Value=""/>
				<Field Name="WitnessName1" Value=""/>
				<Field Name="OtherInfor" Value=""/>
				<Field Name="BadgeNumber" Value=""/>
				<Field Name="Phone" Value=""/>
				<Field Name="Department" Value=""/>
				<Field Name="OfficerName" Value=""/>
				<Field Name="OtherInjuries" Value=""/>
				<Field Name="OtherPassenger" Value=""/>
				<Field Name="YourInjuries" Value=""/>
				<Field Name="YourPassengers" Value=""/>
				<Field Name="OtherDriverPhone" Value=""/>
				<Field Name="OtherDriverAddress" Value=""/>
				<Field Name="OtherDriverName" Value=""/>
				<Field Name="InsuranceCompany" Value=""/>
				<Field Name="Registration" Value=""/>
				<Field Name="VehicleColour" Value=""/>
				<Field Name="VehicleModel" Value=""/>
				<Field Name="VehicleMake" Value=""/>
				<Field Name="OwnerPhone" Value=""/>
				<Field Name="OwnerAddress" Value=""/>
				<Field Name="OwnerName" Value=""/>
				<Field Name="OtherRecovery" Value=""/>
				<Field Name="OtherVehicleDamage" Value=""/>
				<Field Name="YourRecovery" Value=""/>
				<Field Name="YourVehicleDamage" Value=""/>
				<Field Name="AccidentDetails" Value=""/>
				<Field Name="Location" Value=""/>
				<Field Name="Conditions" Value=""/>
				<Field Name="AccidentTime" Value=""/>
				<Field Name="AccidentDate" Value=""/>
				<Field Name="FileCount" Value="0"/>
				<Field Name="RenameSchema" Value="Accident Form -  "/>
				<Field Name="Section" Value="Insurance and Financial Services"/>
				<Field Name="UserHomeFolder" Value="\\NUAN-MOBAD01\HOME\Terilynnebrown"/>
				<Field Name="UserEmail" Value="Brownt@saxon.net"/>
				<Field Name="UserName" Value="terilynnebrown"/>
				<Field Name="FormName" Value="Accident Damage Report"/>
				<Field Name="JobID" Value="4088323595-57129-17284-143-80"/>
			</KnowledgeFields>
		</KnowledgeObject>
	</KnowledgeObjects>
</AutoStore>
