<?xml version="1.0" encoding="utf-8"?>
<AutoStore NSI_SIG2="46AEE51206C72A76777089D2F1ADDA4C77B750E28645C8E65EE3272676653B1F985BCF682F220F39F6D5459AAA97C89A">
	<Header Version="2" DateCreated="2018-06-06" TimeCreated="17:26:49" AUTHOR="" COMMENTS=""/>
	<KnowledgeObjects ObjID="2649706251-34311-17487-174-30">
		<KnowledgeObject ObjID="2064777192-17405-17786-135-126">
			<KnowledgeFields>
				<Field Name="WitnessMobile2" Value=""/>
				<Field Name="WitnessPhone2" Value=""/>
				<Field Name="WitnessAddress2" Value=""/>
				<Field Name="WitnessName2" Value=""/>
				<Field Name="WitnessMobile1" Value=""/>
				<Field Name="WitnessPhone1" Value=""/>
				<Field Name="WitnessAddress1" Value=""/>
				<Field Name="WitnessName1" Value=""/>
				<Field Name="OtherInfor" Value=""/>
				<Field Name="BadgeNumber" Value=""/>
				<Field Name="Phone" Value=""/>
				<Field Name="Department" Value=""/>
				<Field Name="OfficerName" Value=""/>
				<Field Name="OtherInjuries" Value=""/>
				<Field Name="OtherPassenger" Value=""/>
				<Field Name="YourInjuries" Value=""/>
				<Field Name="YourPassengers" Value=""/>
				<Field Name="OtherDriverPhone" Value=""/>
				<Field Name="OtherDriverAddress" Value=""/>
				<Field Name="OtherDriverName" Value=""/>
				<Field Name="InsuranceCompany" Value=""/>
				<Field Name="Registration" Value=""/>
				<Field Name="VehicleColour" Value=""/>
				<Field Name="VehicleModel" Value=""/>
				<Field Name="VehicleMake" Value=""/>
				<Field Name="OwnerPhone" Value=""/>
				<Field Name="OwnerAddress" Value=""/>
				<Field Name="OwnerName" Value=""/>
				<Field Name="OtherRecovery" Value=""/>
				<Field Name="OtherVehicleDamage" Value=""/>
				<Field Name="YourRecovery" Value=""/>
				<Field Name="YourVehicleDamage" Value=""/>
				<Field Name="AccidentDetails" Value=""/>
				<Field Name="Location" Value="717 Hamilton St, Allentown, PA 18101, USA"/>
				<Field Name="Conditions" Value="It was raining and snowing"/>
				<Field Name="AccidentTime" Value="12:30"/>
				<Field Name="AccidentDate" Value="6/6/2018"/>
				<Field Name="FileCount" Value="0"/>
				<Field Name="RenameSchema" Value="Accident Form - 6/6/2018 12:30"/>
				<Field Name="Section" Value="Insurance and Financial Services"/>
				<Field Name="UserHomeFolder" Value="\\NUAN-MOBAD01\HOME\jpitelephone"/>
				<Field Name="UserEmail" Value="jeffrey.pelliconi@nuance.com"/>
				<Field Name="UserName" Value="jpitelephone"/>
				<Field Name="FormName" Value="Accident Damage Report"/>
				<Field Name="JobID" Value="2064777192-17405-17786-135-126"/>
			</KnowledgeFields>
		</KnowledgeObject>
	</KnowledgeObjects>
</AutoStore>
